beets_inlineplus-0.1.0.dist-info/licenses/LICENSE
beetsplug/__init__.py
beetsplug/inlineplus.py
beets_inlineplus-0.1.0.dist-info/METADATA
beets_inlineplus-0.1.0.dist-info/WHEEL
beets_inlineplus-0.1.0.dist-info/top_level.txt
beets_inlineplus-0.1.0.dist-info/RECORD
